{
    "ID": 1970.0,
    "Nome": "Sorrow",
    "Artista": "Michael Sullivan",
    "Tom": "G",
    "Capotraste": "True ",
    "Letra_cifra": " INTRO: Em    D    G    Em    B4/7\n\n Em   Em7+                 Em7      Em6\n Love,    it is almost the morning\n                   E7\n And I see in your eyes\n                Am\n Much time left for us...\n       Am  Am7+                Am7  Am6\n\"Cause you,    don't belong to me\n                 Am\n Someone else is calling\n        B7          Em\n So you have to go away.\n\n     Em   Em7+                  Em7    Em6\n Oh, Here,    will stay with my gloom\n                   E7\n Having nothing to do\n                   Am\n To keep you by my side...\n    Am    Am7+                Am7     Am6\n Oh Woman,    you are sweet surrender\n                  F#7\n That I want to remember\n         B4/7             B7\n And now this is all I've got\n\n   Am7 D7     G7+ C7+\n My sorrow,    sorrow,\nF#m5-/7 B7                   Em   E7\n Sorrow,    'cause you went away\n   Am7 D7     G7+ C7+\n My sorrow,    sorrow,\nF#m5-/7 B7                   Em\n Sorrow,    'cause you went away\n                             Am  B7  :\n            'cause you went away.\n\n FLUTE SOLO: : Em Em7+ : Em7 Em6 : E7 Am\n\n Am    Am7+                Am7     Am6\n Woman,    you are sweet surrender\n                  F#7\n That I want to remember\n         B4/7             B7\n And now this is all I've got\n\n   Am7 D7     G7+ C7+                      \n My sorrow,    sorrow,                     \n  \\\n  :\nF#m5-/7 B7                   Em  E7      \n Sorrow,    'cause you went away         \n    :\n    \\  [Repeat 4 Times and Fade Out]\n   Am7 D7     G7+ C7+                      \n My sorrow,    sorrow,                     \n  /\n  :\nF#m5-/7 B7                   Em  E7      \n Sorrow,    'cause you went away         \n    :\n    /",
    "Compositor": "Composição de Mark / Michael Sullivan / R"
}