{
    "ID": 2280,
    "Nome": "The Love I Need",
    "Artista": "Jimmy Cliff",
    "Tom": "C",
    "Capotraste": "Capotraste",
    "Letra_cifra": "Am           G\nYou know I can't get\nAm             G\nI say I can't get\nAm           G\nYou know I can't get\nAm\nThe love I need\nAm\nThe love I need\nC             G\nMaybe I'm just wasting time\nAm        Em\nTrying to get a fish on a line\nF               Am       G\nAnyway, I'm a man, so I got to try\nC             G\nMaybe I'm just hard to please\nAm       Em\nBut then again, it's just my needs\nF                 Am       G\nMaybe it's just the way that I am high\nAm          G\nBecause I can't get\nAm            G\nNo, no, I can't get\nAm           G\nYou know I can't get\nAm\nThe love I need\nAm\nThe love I need\nC               G\nI know that it's love it takes\nAm       Em\nTo keep this man in me awake\nF                  Am      G\nAnd I find it hard to compromise\nC            G\nThere's no mountain hard to climb\nAm      Em\nWhen I got the love I need full time\nF               Am        G\nTo keep me satisfied and it's just my size\nAm           G\nTherefore I can't get\nAm           G\nYou know I can't get\nAm             G\nNo, no, I, I can't get\nAm\nThe love I need\nAm\nThe love I need\nAm\nI don't want no part-time love\nAm\nI don't want no part-time love\nAm\nDon't want no part-time love\nAm\nDon't want no part-time love\nAm          G\nBecause I can't get\nAm             G\nI know I can't get\nAm             G\nNo, no, I, I can't get\nAm\nThe love I need\nAm\nThe love I need\nAm\nDon't want no part-time love (The love I need)\nAm\nAnd I don't want no part-time love (The love I need)\nAm\nDon't want no part-time love (The love I need)\nAm\nDon't want no part-time love (The love I need)\nAm\nPart time love (The love I need)\nAm\n(The love I need)",
    "Compositor": "Jimmy Cliff. Esta informação está errada? Nos avise."
}