{
    "ID": 2293.0,
    "Nome": "Rua Ramalhete",
    "Artista": "Tavito",
    "Tom": "F",
    "Capotraste": "Capotraste na 3ª casa",
    "Letra_cifra": "[Intro] Am  F/A  B/A  E7(4)\n\nAm      Am/G         F7M\nSem  querer fui me lembrar\n       G/B         C9\nDe uma rua e seus ramalhetes\n    F7M               C9             E7(4) E/G#\nO amor  anotado em bilhetes  daquelas tardes\n\nAm9          Am7/G     F7M\nNo muro      do Sacré-Coeur\n      G/B           C9\nDe uniforme e olhar de rapina\n       F7M                C9                E7(4)  E7\nNossos bailes no clube da esquina   quanta saudade\n\nA9                   B/A\nMuito  prazer, vamos dançar\n             G#m          C#7(4) C#7\nQue eu vou falar no seu ouvido\nF#7(4)     F#7     B7(4) B7         E7(4)        E7\nCoisas que vão fazer  você tremer dentro do vestido\nA9                 B/A\nVamos  deixar tudo rolar\n            G#m          C#7(4) C#7\nE o som dos Beatles na vitro____la\n\n  F#9               B9           F#9         A9    B9\nSerá      que algum dia eles vêm     aí\n   F#9           B9                  C#9  C#7(4)  C#7  C#m7  C#7\nCantar     as canções que a gente quer ouvir\n\n[Solo] F#m  F#m5+  E7(4)  E7  A7M \n       D7M  D#º  C#7(4)  C#7  C#m7  C#7 \n       F#m  F#m5+  E7(4)  E7  A7M \n       D7M  D#º  C#7(4)  C#7  Bm7  E7(4)  E7\n\nAm7       Am7/G         F9\n Sem querer     fui me lembrar",
    "Compositor": "Ney Azambuja / Tavito. Esta informação está errada? Nos avise."
}