{
    "ID": 230.0,
    "Nome": "Fechei a Porta",
    "Artista": "Jamelão",
    "Tom": "A",
    "Capotraste": "True ",
    "Letra_cifra": "[Intro] Em7(5-)  D#m7  Dm7\n        G7(13-)  Cm7  F7(13-)  A#7M\n\n[Primeira Parte]\n\nEm7(5-)        F/D#\nEu não quero mais amar\n             Dm7         C#º Eº Gº\nPra não sofrer   ingratidão\n   Cm7         Dm7    Fm7(5-)  G7\nDepois do que eu passei\n          Cm11        F7(9-)   A#6 A#7(4) A#7(9)\nFechei a porta do meu co-----ração\n\nEm7(5-)        F/D#\nEu não quero mais amar\n             Dm7         C#º Eº  Gº\nPra não sofrer   ingratidão\n   Cm7         Dm7    Fm7(5-)  G7\nDepois do que eu passei\n          Cm11        F7(9-)   A#6 A#7(4) A#7(9)\nFechei a porta do meu co-----ração\n\n[Refrão]\n\n         D#6 D#m6         A#7M  G7\nEu dei a ela     todo o carinho\n          Cm7     F7(9)     A#6 A#7(4) A#7(9)\nE, no entanto, acabei  sozinho\n\n         D#6 D#m6         A#7M  G7\nEu dei a ela     todo o carinho\n          Cm7     F7(9)     A#6 A#7(4) A#7(9)\nE, no entanto, acabei  sozinho\n\n Em7(5-)  D#m7  Dm7\n G7(13-)  Cm7\n F7(13-)  A#7M\n\n[Primeira Parte]\n\nEm7(5-)        F/D#\nEu não quero mais amar\n             Dm7         C#º Eº Gº\nPra não sofrer   ingratidão\n   Cm7         Dm7    Fm7(5-)  G7\nDepois do que eu passei\n          Cm11        F7(9-)   A#6 A#7(4) A#7(9)\nFechei a porta do meu co-----ração\n\nEm7(5-)        F/D#\nEu não quero mais amar\n             Dm7         C#º Eº Gº\nPra não sofrer   ingratidão\n   Cm7         Dm7    Fm7(5-)  G7\nDepois do que eu passei\n          Cm11        F7(9-)   A#6 A#7(4) A#7(9)\nFechei a porta do meu co-----ração\n\n[Refrão]\n\n         D#6 D#m6         A#7M  G7\nEu dei a ela     todo o carinho\n          Cm7     F7(9)     A#6 A#7(4) A#7(9)\nE, no entanto, acabei  sozinho\n\n         D#6 D#m6         A#7M  G7\nEu dei a ela     todo o carinho\n          Cm7     F7(9)     A#6 A#7(4) A#7(9)\nE, no entanto, acabei  sozinhO\n\n         D#6 D#m6         A#7M  G7\nEu dei a ela     todo o carinho\n          Cm7     F7(9)     A#6 A#7(4) A#7(9)\nE, no entanto, acabei  sozinho\n\n         D#6 D#m6         A#7M  G7\nEu dei a ela     todo o carinho\n          Cm7     F7(9)     A#6 A#7(4) A#7(9)\nE, no entanto, acabei  sozinhO\n\n Em7(5-)  D#m7  Dm7\n G7(13-)  Cm7\n F7(13-)  A#7M\n Em7(5-)",
    "Compositor": "Composição de Ferreira dos Santos / Sebastião Motta"
}