{
    "ID": 2308.0,
    "Nome": "Palco",
    "Artista": "Gilberto Gil",
    "Tom": "C#m",
    "Capotraste": "Capotraste",
    "Letra_cifra": "[Intro] E7M  Bm7  E7  A7M  C/D\n        E7M  Bm7  E7  A7M  C/D\n\n E7M     F#m7      G#m7        A7M\nSubo nesse palco, minha alma cheira a talco\n  B7(4/9)  C#m7   G#7(5+)      A7M\nComo bumbum de bebê,     de      bebê\n E7M      F#m7       G#m7      A7M       B7\nMinha aura clara só quem é clarividente pode ver\n C#m7  B7\nPode  ver\n E7M       F#m7        G#m7      A7M\nTrago a minha banda, só quem sabe onde é Luanda\n B7(4/9)    C#m7     G#7(5+)   A7M\nSaberá lhe dar valor, dar valor\n E7M      F#m7        G#m7         A7M     B7\nVale quanto pesa prá quem preza o louco bumbum do tambor\n C#m7 B7\nDo tambor\n\n C#m7      G#7(5+)\nFogo eterno pra afugentar\nA7M        B7(4/9)\nO inferno pra outro lugar\n C#m7      G#7(5+)\nFogo eterno pra consumir\nA7M        B7(4/9)\nO inferno, fora daqui\n C#m7      G#7(5+)      A7M         B7(4/9)\nLa laia, laia, laia laia laia             Fora daqui\n C#m7      G#7(5+)      A7M         B7(4/9)\nLa laia, laia, laia laia laia             Fora daqui\n C#m7      G#7(5+)      A7M         B7(4/9)\nLa laia, laia, laia laia laia             Fora daqui\n Cº\n\n E7M      F#m7          G#m7        A7M\nVenho para a festa, sei que muitos têm na testa\n    B7(4/9)    C#m7   G#7(5+)   A7M\nO deus Sol como um sinal    um sinal\nE7M     F#m7         G#m7       A7M       B7\nEu, como devoto, trago um cesto de alegrias de quintal\n C#m7   B7\nDe quintal\n E7M     F#m7       G#m7       A7M\nHá também um cântaro, quem manda é a deusa Música\n B7(4/9)      C#m7     G#7(5+)   A7M\nPedindo prá deixar,    pra deixar\n E7M     F#m7     G#m7        A7M        B7\nDerramar o bálsamo, fazer o canto, cantar o cantar\n C#m7     B7\nLá, lá, iá\n\n( E7M  Bm7  E7(9) )\n( A7M  Am7  D7(9) )",
    "Compositor": "Gilberto Gil. Esta informação está errada? Nos avise."
}