{
    "ID": 2347.0,
    "Nome": "Reality",
    "Artista": "Richard Sanderson",
    "Tom": "C",
    "Capotraste": "Capotraste",
    "Letra_cifra": "[Primeira Parte]\n\nG                    Bm\nMet you by surprise, I didn't realize\nDm                           E    D  E\nThat my life would change forever\nAm                      Cm\nSaw you standing there, I didn't know I cared\nBm7                  Em7            A7  D7\nThere was something special in the air\n\n[Refrão]\n\nG                  B7\nDreams are my reality\n                       Em7   A7\nThe only kind of real fantasy\n          C            D7\nIllusions are a common thing\n  Bm7              Em7\nI try to live in dreams\nAm7                          F D7\nIt seems as if it's meant to be\nG                  B7\nDreams are my reality\n                    Em7      A7\nA different kind of reality\n           C            D7\nI dream of loving in the night\n    Bm7              Em7\nAnd loving seems alright\nAm7                 D7    C G\nAlthough it's only fantasy\n\n[Segunda Parte]\n\nG                Bm\nIf you do exist, honey don't resist\nDm                   E     (D E)\nShow me a new way of loving\nAm                      Cm\nTell me that it's true, show me what to do\nBm7               Em7            A7  D7\nI feel something special about you\n\n[Refrão]\n\nG                  B7\nDreams are my reality\n                 Em7     A7\nThe only kind of reality\n          C            D7\nMaybe my foolishness has past\n    Bm7              Em7\nAnd maybe now at last\nAm7                 F      D7\nI'll see how a real thing can be\nG                  B7\nDreams are my reality\n                   Em7            A7\nA wondrous world where I like to be\n           C               D7\nI dream of holding you all night\n    Bm7                Em7\nAnd holding you seems right\nAm7                 D7   C G\nPerhaps that's my reality\n\n[Terceira Parte]\n\nG                    Bm\nMet you by surprise, I didn't realize\nDm                        E      (D E)\nThat my life would change forever\nAm                      Cm\nTell me that it's true, Feelings that are cue\nBm7              Em7           A7  D7\nI feel something special about you\n\n[Refrão]\n\nG                  B7\nDreams are my reality\n                 Em7             A7\nA wondrous world where I like to be\n          C            D7\nIllusions are a common thing\n  Bm7            Em7\nI try to live in dreams\nAm7                F    D7\nAlthough it's only fantasy\nG                  B7\nDreams are my reality\n                   Em7            A7\nI like to dream of you close to me\n           C             D7\nI dream of loving in the night\n    Bm7              Em7\nAnd loving you seems right\nAm7                 D7   C G\nPerhaps that's my reality",
    "Compositor": "Vladimir Cosma. Esta informação está errada? Nos avise."
}