{
    "ID": 2518,
    "Nome": "Adivinha o Que",
    "Artista": "Lulu Santos",
    "Tom": "Em",
    "Capotraste": "Capotraste",
    "Letra_cifra": "[Intro] Em7  Bm7  Am7 ( Em7  B7(9+) )\n\nEm7\nAinda lembro aquela noite\n                      Bm7\nSó porque eu cheguei mais tarde\nAm7\nInda arde a lembranca de te ver\n             Em7    B7(9+)\nAli tao contrariada\n\n Em7\nMeu bem, meu bem será que você\n             Bm7\nNão vê, nao houve nada\n\n Am7                                    Em7   B7(9+)\nSó o passado rondando minha porta feito alma penada\n Em7                                   Bm7\nVocê vive me dizendo que o pecado mora ao lado\n     Am7\nPor favor, não entra nessa\n                               Em7\nPorque um dia inda te explico direito\n\n    Em7                                  Bm7\nEu sei,eu sei que esse caso ta meio mal contado\n     Am7\nMas você pode ter certeza\n                           Em7     B7(9+)\nNosso amor é quase sempre perfeito\n\n           Em7\nPorque eu só faço com você\n D9\nSó quero com você\n A9             Bb5  B5  C5  B5\nSó gosto com você\n  Em7           B7(9+)\nAdivinha o que?\n\n           Em7\nPorque eu só faço por você\n D9\nSó quero com você\n A9             Bb5  B5  C5  B5\nSó gosto com você\n  Em7          B7(9)\nAdivinha o que?\n\n[Solo] Em7  Bm7  Am7 ( Em7  B7(9+) )\n\n           Em7\nPorque eu só faço por você\n D9\nSó quero com você\n A9             Bb5  B5  C5  B5\nSó gosto com você\n  Em7          B7(9)\nAdivinha o que?\n\n\nEm7\nAinda lembro aquela noite\n                      Bm7\nSó porque eu cheguei mais tarde\nAm7\nInda arde a lembranca de te ver\n             Em7    B7(9+)\nAli tao contrariada\n\n Em7\nMeu bem, meu bem será que você\n             Bm7\nNão vê, nao houve nada\n\n Am7                                    Em7   B7(9+)\nSó o passado rondando minha porta feito alma penada\n\n           Em7\nPorque eu só faço por você\n D9\nSó quero com você\n A9             Bb5  B5  C5  B5\nSó gosto com você\n  Em7          B7(9)\nAdivinha o que?",
    "Compositor": "Lulu Santos. Esta informação está errada? Nos avise."
}