{
    "ID": 2658,
    "Nome": "Baile Dos Passarinhos",
    "Artista": "Gugu",
    "Tom": "C",
    "Capotraste": "Capotraste",
    "Letra_cifra": "                   C\nPassarinho quer dançar, o rabicho balançar\n                   G\nPorque acaba de nascer, tchu tchu tchu tchu\n                   Dm                         G7\nPassarinho quer dançar, quer ter canto pra cantar\n             C\nAlegria de viver, tchu tchu tchu tchu\n\nSeu biquinho quer abrir, as asinhas sacudir\n                G\nE o rabicho remexer, tchu tchu tchu tchu\n                 G7\nJoelhinho vai dobrar, dois saltinhos só pra ver\n        C  G7\nVamos voar\n\nC                          G7\nÉ dia de festa dança sem parar\nDm         G7                    Dm          G7\nE depois voar no azul, cruzar de norte a sul\n          C\nO céu e o mar\n\nG7                 C\nPassarinho quer dançar, o rabicho balançar\n G\nPorque acaba de nascer, tchu tchu tchu tchu\n                  Dm                  G7\nNo seu ninho dançará, passarinho passará\n               C\nA alegria de viver, tchu tchu tchu tchu\n\nSeu biquinho quer abrir, as asinhas sacudir\n                G\nE o rabicho remexer, tchu tchu tchu tchu\n                 G7\nJoelhinho vai dobrar, dois saltinhos só pra ver\n        C  G7\nVamos voar\n\nC                          G7\nÉ dia de festa dança sem parar\nDm         G7                    Dm          G7\nE depois voar no azul, cruzar de norte a sul\n          C\nO céu e o mar",
    "Compositor": "Edgard Poças / T. Randall / W. Thomas. Esta informação está errada? Nos avise."
}