{
    "ID": 2823.0,
    "Nome": "Transas",
    "Artista": "Ritchie",
    "Tom": "D",
    "Capotraste": "Capotraste",
    "Letra_cifra": "[Intro] D  Bm7  D/G  G/A\n        D  Bm7  D/G  G/A\n\nD                             Bm7\n  Tanto tempo faz que a gente transa\n         F#m7(4)     G/A\nE não se conversou\nD                                Bm7\n  Tanto vício, tanta fuga pra saber\n  F#m7(4)  Gm6\nSe é amor\n                       D/F#        Gm6\nSei que você pensa que passa e vai\n   D/F#\nSó transas\nGm/6                    D/F#      E  Eb7M\n   Faz de conta que não se quer mais\n                 G/A\nÉ transa e tanto faz\n                 D   Bm7\nQuando se quer mais\n      F#m7(4)        G/A\nA gente diz 'bye bye'\n               D  Bm7\nA gente quer mais\n          F#m7(4)    G/A\nE finge que satisfaz\nD                                      Bm7\n  É moderno, é certo, sei que muitos querem\n          F#m7(4)  G/A\nEssa forma de amor\nD                                 Bm7\n  Se chega perto, é certo, sem paixão\n       F#m7(4)     Gm6\nMas também sem dor\n                       D/F#        Gm6\nA gente pensa que isso passa e vai\n   D/F#      Gm6\nSó transas\n                       D/F#   E  Eb7M\nFaz de conta que não se ama mais\n                 G/A\nÉ transa e tanto faz\n                  D   Bm7\nE quando se quer mais\n       F#m7(4)        G/A\nA gente diz 'bye bye'\n               D  Bm7\nA gente quer mais\n             F#m7(4)   G/A\nMas finge que satisfaz",
    "Compositor": "Nico Rezende / Paulinho Lima. Esta informação está errada? Nos avise."
}