{
    "ID": 3276.0,
    "Nome": "Sobre o Tempo",
    "Artista": "Nenhum de Nós",
    "Tom": "G",
    "Capotraste": "Capotraste",
    "Letra_cifra": "[Intro] G  C  Em  D  C\n\nEm\nOs homens trocam as famílias\nC\nAs filhas, filhas de suas filhas\nEm                    D           C\nE tudo aquilo que não podem entender\nEm\nOs homens criam os seus filhos\nC\nVerdadeiros ou adotivos\nEm               D                C\nCriam coisas que não deviam conceber\nG\nO tempo passa e nem tudo fica\n  C\nA obra inteira de uma vida\nEm\nO que se move e\n      D              C\nO que nunca vai se mover ê êêê\n\nG\nO tempo passa e nem tudo fica\n  C\nA obra inteira de uma vida\nEm\nO que se move e\n      D              C\nO que nunca vai se mover ê êêê\n\nSem mover ê êêê\nEm\nO passado está escrito\nC                          Em\nNas colunas de um edifício     ou\n\nNa geleira\n     D          C\nOnde um mamute foi morrer\nEm\nO tempo engana aqueles\n\nQue pensam\n    Bm\nQue sabem demais\n\nQue juram que pensam\n  Am\nExistem também aqueles que juram\n       C\nSem saber\n\nG\nO tempo passa e nem tudo fica\n  C\nA obra inteira de uma vida\nEm\nO que se move e\n      D              C\nO que nunca vai se mover ê êêê\nG\nO tempo passa e nem tudo fica\n  C\nA obra inteira de uma vida\nEm\nO que se move e\n      D              C\nO que nunca vai se mover ê êêê\n\nSe mover\n\n[Final] G  C  Em  D  C",
    "Compositor": "Thedy Corrêa. Esta informação está errada? Nos avise."
}