{
    "ID": 3368.0,
    "Nome": "Spending My Time",
    "Artista": "Roxette",
    "Tom": "Db",
    "Capotraste": "Capotraste na 2ª casa",
    "Letra_cifra": "[Primeira Parte]\n\n           Em              Am        D4    D\nWhat's the time? Seems it's already morning\n           Em              C          D4 D\nI see the sky, it's so beautiful and blue\n          Em          C          D4    D             \nThe tv's on, but the only thing showing is a picture\n     A Am\nOf you\n\n         Em     Am           D4    D\nOh I get up and make myself some coffee\n         Em                  C           D4  D\nI try to read a bit but the story's to thin\n             Em             C                  D4        \nI thank the lord above that you're not here to see\n  D                  A   Am\nMe in the shape I'm in\n\n[Refrão]\n\n             D   D4 D         \nSpending my time      watching\n     A\nThe days go by\n             Bm         \nFeeling so small\n                G\nI stare at the wall\n             Em   \nHoping that you\n  G          A\nThink of me too\n                 Bm\nI'm spending my time\n\n[Segunda Parte]\n\n          Em       \nI try to call but\n   Am\nI don't know what\n    D4     D\nTo tell you\n           Em\nI leave a kiss on\n     Am            D4  D\nYour answering machine\n             Em          \nOh help me please\n          Am         \nIs there someone who can\n D4      D\nMake me wake up\n            A   Am\nFrom this dream?\n\n[Refrão]\n\n             D   D4 D         \nSpending my time      watching\n     A\nThe days go by\n             Bm         \nFeeling so small\n                G\nI stare at the wall\n             Em   \nHoping that you\n    G            A\nAre missing me too\n                 D  D4  D\nI'm spending my time\n              A\nWatching the sun go down\n                      Bm         \nI fall asleep to the sound\n                 G       \nOf \"Tears of a Clown\"\n            Em      A\nA prayer gone blind\n                 Bm  (A)  Em\nI'm spending my time\n\nSolo\n\nE|-----------9--|\nB|-0-5-7-9-7----|\nG|--------------|\nD|--------------|\nA|--------------|\nE|--------------|\n\n[Ponte]\n\nEm                G        \n  My friends keep telling me\n     D           C\nHey life will go on\nEm           G \n  Time will make sure\n         D      \nI'll get over you\nEm            G\n  This silly game of love\n      D           A         \nYou play, you win only\n    C   B\nTo lose\n\n[Refrão]\n\n           E                \nSpending my time\n              B\nWatching the days go by\n            C#m           \nFeeling so small\n                A\nI stare at the wall\n             F#m  \nHoping that you\nA             B\nThink of me too\n                  E \nI'm spending my time\n              B\nWatching the sun go down\n                      C#m                \nI fall asleep to the sound\n                 A\nOf \"Tears of a Clown\"\n               F#m    B \nA prayer gone blind\n                 C#m ( B )\nI'm spending my time\n\n[Final] A  B  E  F#m  A  B  E",
    "Compositor": "Mats Persson / Per Gessle. Esta informação está errada? Nos avise."
}