{
    "ID": 5151,
    "Nome": "O Que Vai Ser de Nós",
    "Artista": "Zezé Di Camargo e Luciano",
    "Tom": "F",
    "Capotraste": "Capotraste",
    "Letra_cifra": "[Intro] F  A  Bb  Am  Gm  C  F  Bb\n\nF\nDiz nada não\n                                                 C\nApenas vai pegando as minhas coisas e amontoando aí no chão\n                                                   Bb\nEnquanto eu vou tentando achar um jeito de tirar você do coração\n                                              C           Bb C\nEu tenho que levar porradas por ter aprontado outra vez\n\n   F\nDe solidão\n                                                     C\nEu já fiz faculdade e hoje sei o que é perder uma grande paixão\n\nEu sei cuidar de mim, eu vou à luta, eu saio dessa\n     Bb                   C\nNão tem nada não, não tem nada não\n\n         F\nEu vou pagar pra ver\n                                            A\nMas na verdade eu sou completamente louco por você\n                                       Bb         Am\nEu sei que eu pisei na bola e agora eu posso ver\n       Gm                        C\nQue só aprontei, te machuquei, te fiz sofrer\n\n          F\nNão quero te perder\n                                          A\nMas não sou eu quem vai interferir na sua decisão\n                                                 Bb          Am\nMas saiba que o destino desse nosso amor está em suas mãos\n     Gm           C                     F\nE é você quem vai dizer o que vai ser de nós\n\n[Intro] .: F  A  Bb  Am  Gm  C  F  Bb\n\n   F\nDe solidão\n                                                     C\nEu já fiz faculdade e hoje sei o que é perder uma grande paixão\n\nEu sei cuidar de mim, eu vou à luta, eu saio dessa\n     Bb                   C\nNão tem nada não, não tem nada não\n\n         F\nEu vou pagar pra ver\n                                            A\nMas na verdade eu sou completamente louco por você\n                                       Bb         Am\nEu sei que eu pisei na bola e agora eu posso ver\n       Gm                        C\nQue só aprontei, te machuquei, te fiz sofrer\n\n          F\nNão quero te perder\n                                          A\nMas não sou eu quem vai interferir na sua decisão\n                                                 Bb          Am\nMas saiba que o destino desse nosso amor está em suas mãos\n     Gm           C                     F\nE é você quem vai dizer o que vai ser de nós\n\n        F\nNão quero te perder\n                                          A\nMas não sou eu quem vai interferir na sua decisão\n                                                 Bb          Am\nMas saiba que o destino desse nosso amor está em suas mãos\n     Gm           C                     F\nE é você quem vai dizer o que vai ser de nós\n\n Am\n     Gm           C                     F\nE é você quem vai dizer o que vai ser de nós",
    "Compositor": "Carlos Randall / Danimar / Tivas. Esta informação está errada? Nos avise."
}